{
    "name": "Orc female",
    "type_name": "head",
    "layer_1": {
        "male": "head/heads/orc/female/",
        "female": "head/heads/orc/female/"
    },
    "variants": [
        {
            "name": "light",
            "full_name": "",
            "description": "",
            "spell": 1,
            "rare": 1,
            "element": 1
        },
        {
            "name": "amber",
            "full_name": "",
            "description": "",
            "spell": 1,
            "rare": 1,
            "element": 1
        },
        {
            "name": "olive",
            "full_name": "",
            "description": "",
            "spell": 1,
            "rare": 1,
            "element": 1
        },
        {
            "name": "taupe",
            "full_name": "",
            "description": "",
            "spell": 1,
            "rare": 1,
            "element": 1
        },
        {
            "name": "bronze",
            "full_name": "",
            "description": "",
            "spell": 1,
            "rare": 1,
            "element": 1
        },
        {
            "name": "brown",
            "full_name": "",
            "description": "",
            "spell": 1,
            "rare": 1,
            "element": 1
        },
        {
            "name": "black",
            "full_name": "",
            "description": "",
            "spell": 1,
            "rare": 1,
            "element": 1
        },
        {
            "name": "lavender",
            "full_name": "",
            "description": "",
            "spell": 1,
            "rare": 1,
            "element": 1
        },
        {
            "name": "blue",
            "full_name": "",
            "description": "",
            "spell": 1,
            "rare": 1,
            "element": 1
        },
        {
            "name": "zombie_green",
            "full_name": "",
            "description": "",
            "spell": 1,
            "rare": 1,
            "element": 1
        },
        {
            "name": "green",
            "full_name": "",
            "description": "",
            "spell": 1,
            "rare": 1,
            "element": 1
        },
        {
            "name": "pale_green",
            "full_name": "",
            "description": "",
            "spell": 1,
            "rare": 1,
            "element": 1
        },
        {
            "name": "bright_green",
            "full_name": "",
            "description": "",
            "spell": 1,
            "rare": 1,
            "element": 1
        },
        {
            "name": "dark_green",
            "full_name": "",
            "description": "",
            "spell": 1,
            "rare": 1,
            "element": 1
        }
    ],
    "match_body_color": true,
    "animations": [
        "spellcast",
        "thrust",
        "walk",
        "slash",
        "shoot",
        "hurt",
        "watering",
        "idle",
        "jump",
        "run",
        "sit",
        "emote",
        "climb",
        "combat",
        "1h_slash",
        "1h_backslash",
        "1h_halfslash"
    ]
}