{
    "name": "Heater Shield Base",
    "type_name": "shield",
    "layer_1": {
        "male": "shield/heater/original/wood/bg/",
        "female": "shield/heater/original/wood/bg/"
    },
    "layer_2": {
        "male": "shield/heater/original/wood/fg/",
        "female": "shield/heater/original/wood/fg/"
    },
    "variants": [
        "brown",
        "coffee",
        "oak",
        "tan",
        "umber"
    ],
    "animations": [
        "spellcast",
        "thrust",
        "walk",
        "slash",
        "shoot",
        "hurt",
        "watering",
        "idle",
        "jump",
        "run",
        "sit",
        "emote",
        "climb",
        "combat",
        "1h_slash",
        "1h_backslash",
        "1h_halfslash"
    ]
}